[
  {
    "id": "dQw4w9WgXcQ",
    "title": "5 Forgotten Disasters Nobody Talks About",
    "publishDate": "2025-02-22",
    "thumbnail": "https://img.youtube.com/vi/dQw4w9WgXcQ/maxresdefault.jpg"
  },
  {
    "id": "dQw4w9WgXcQ",
    "title": "The 1970 Bhola Cyclone: The Deadliest Storm in History",
    "publishDate": "2025-02-15",
    "thumbnail": "https://img.youtube.com/vi/dQw4w9WgXcQ/maxresdefault.jpg"
  },
  {
    "id": "dQw4w9WgXcQ",
    "title": "When Kilauea Woke Up: The 2018 Lower East Rift Zone Eruption",
    "publishDate": "2025-02-08",
    "thumbnail": "https://img.youtube.com/vi/dQw4w9WgXcQ/maxresdefault.jpg"
  },
  {
    "id": "dQw4w9WgXcQ",
    "title": "Camp Fire: How Paradise Burned in 85 Minutes",
    "publishDate": "2025-01-25",
    "thumbnail": "https://img.youtube.com/vi/dQw4w9WgXcQ/maxresdefault.jpg"
  },
  {
    "id": "dQw4w9WgXcQ",
    "title": "Japan 2011: The Day the Ocean Came Inland",
    "publishDate": "2025-01-18",
    "thumbnail": "https://img.youtube.com/vi/dQw4w9WgXcQ/maxresdefault.jpg"
  },
  {
    "id": "dQw4w9WgXcQ",
    "title": "The Johnstown Flood: When a Dam Broke and Killed 2,209 People",
    "publishDate": "2025-01-11",
    "thumbnail": "https://img.youtube.com/vi/dQw4w9WgXcQ/maxresdefault.jpg"
  }
]
